iterio/__init__.py
iterio/py.typed
iterio-0.1.0.dist-info/LICENSE
iterio-0.1.0.dist-info/WHEEL
iterio-0.1.0.dist-info/METADATA
iterio-0.1.0.dist-info/RECORD
